{
  "task_id": "fc-01KMJQK3GXBG0ZS22ZAXXCR13N",
  "status": "COMPLETED",
  "progress": 100,
  "current_step": "COMPLETE",
  "graph_data": {
    "nodes": [
      {
        "id": "0xf46bfb21ccb72e83db06b23d3f05e86b3e259efd",
        "risk_label": "MALICIOUS",
        "cluster_id": 2,
        "risk_score": 0.95,
        "attributes": {
          "handle": "edvacrypto",
          "trust_score": 0.26,
          "follower_count": 0,
          "post_count": 0,
          "picture_url": "",
          "owned_by": "0x6b6d9189486d9326c4676167bfe5e2e448d291e8",
          "reasons": [
            "High Co-owner relationship (100.00%) +50",
            "Batch Creation detected (std: 0.005021) +15",
            "Low Social interaction (0.00%) +10",
            "Very Low Trust Score (avg: 0.26) +20"
          ]
        }
      },
      {
        "id": "0xffcb4b09f394f452c5100f0152cef89aede9973c",
        "risk_label": "MALICIOUS",
        "cluster_id": 2,
        "risk_score": 0.95,
        "attributes": {
          "handle": "edvardas",
          "trust_score": 0.26,
          "follower_count": 0,
          "post_count": 0,
          "picture_url": "",
          "owned_by": "0x6b6d9189486d9326c4676167bfe5e2e448d291e8",
          "reasons": [
            "High Co-owner relationship (100.00%) +50",
            "Batch Creation detected (std: 0.005021) +15",
            "Low Social interaction (0.00%) +10",
            "Very Low Trust Score (avg: 0.26) +20"
          ]
        }
      },
      {
        "id": "0xb88c8ffb879f1e1aba113ae730cd7a4c0e56e3ab",
        "risk_label": "MALICIOUS",
        "cluster_id": 0,
        "risk_score": 0.95,
        "attributes": {
          "handle": "henryinthemorning",
          "trust_score": 0.39,
          "follower_count": 0,
          "post_count": 1,
          "picture_url": "",
          "owned_by": "0x7d78cd9438165feb80057437802aec2a218863ae",
          "reasons": [
            "High Co-owner relationship (97.83%) +50",
            "Batch Creation detected (std: 0.114309) +15",
            "Low Social interaction (0.00%) +10",
            "Very Low Trust Score (avg: 0.80) +20"
          ]
        }
      },
      {
        "id": "0x96924fb77ec718a740cf97519dff4b2dda52b474",
        "risk_label": "MALICIOUS",
        "cluster_id": 0,
        "risk_score": 0.95,
        "attributes": {
          "handle": "wanttokillmyself",
          "trust_score": 0.35,
          "follower_count": 0,
          "post_count": 1,
          "picture_url": "",
          "owned_by": "0x7d78cd9438165feb80057437802aec2a218863ae",
          "reasons": [
            "High Co-owner relationship (97.83%) +50",
            "Batch Creation detected (std: 0.114309) +15",
            "Low Social interaction (0.00%) +10",
            "Very Low Trust Score (avg: 0.80) +20"
          ]
        }
      },
      {
        "id": "0xb9cd598d4fd15c13610b79699828d4290410d2a9",
        "risk_label": "MALICIOUS",
        "cluster_id": 0,
        "risk_score": 0.95,
        "attributes": {
          "handle": "horracetoyall",
          "trust_score": 0.22,
          "follower_count": 0,
          "post_count": 0,
          "picture_url": "",
          "owned_by": "0x7d78cd9438165feb80057437802aec2a218863ae",
          "reasons": [
            "High Co-owner relationship (97.83%) +50",
            "Batch Creation detected (std: 0.114309) +15",
            "Low Social interaction (0.00%) +10",
            "Very Low Trust Score (avg: 0.80) +20"
          ]
        }
      },
      {
        "id": "0x4e5d4fe07250979a03c24c37f69cc83b77f2a008",
        "risk_label": "MALICIOUS",
        "cluster_id": 0,
        "risk_score": 0.95,
        "attributes": {
          "handle": "jimmymtfcker",
          "trust_score": 0.22,
          "follower_count": 0,
          "post_count": 0,
          "picture_url": "",
          "owned_by": "0x7d78cd9438165feb80057437802aec2a218863ae",
          "reasons": [
            "High Co-owner relationship (97.83%) +50",
            "Batch Creation detected (std: 0.114309) +15",
            "Low Social interaction (0.00%) +10",
            "Very Low Trust Score (avg: 0.80) +20"
          ]
        }
      },
      {
        "id": "0x63cff7128d00d024ee724b6f66af1c2a20f69fd8",
        "risk_label": "MALICIOUS",
        "cluster_id": 0,
        "risk_score": 0.95,
        "attributes": {
          "handle": "richardashuman",
          "trust_score": 0.22,
          "follower_count": 0,
          "post_count": 0,
          "picture_url": "",
          "owned_by": "0x7d78cd9438165feb80057437802aec2a218863ae",
          "reasons": [
            "High Co-owner relationship (97.83%) +50",
            "Batch Creation detected (std: 0.114309) +15",
            "Low Social interaction (0.00%) +10",
            "Very Low Trust Score (avg: 0.80) +20"
          ]
        }
      },
      {
        "id": "0xf552d2f3046b41493e8123484c5603358b228de2",
        "risk_label": "MALICIOUS",
        "cluster_id": 0,
        "risk_score": 0.95,
        "attributes": {
          "handle": "lindamarl",
          "trust_score": 0.2,
          "follower_count": 0,
          "post_count": 0,
          "picture_url": "",
          "owned_by": "0x7d78cd9438165feb80057437802aec2a218863ae",
          "reasons": [
            "High Co-owner relationship (97.83%) +50",
            "Batch Creation detected (std: 0.114309) +15",
            "Low Social interaction (0.00%) +10",
            "Very Low Trust Score (avg: 0.80) +20"
          ]
        }
      },
      {
        "id": "0xc905e7b845826dd473f42bae8a2cddbe2c630420",
        "risk_label": "MALICIOUS",
        "cluster_id": 0,
        "risk_score": 0.95,
        "attributes": {
          "handle": "imisa",
          "trust_score": 0.21,
          "follower_count": 0,
          "post_count": 0,
          "picture_url": "",
          "owned_by": "0x7d78cd9438165feb80057437802aec2a218863ae",
          "reasons": [
            "High Co-owner relationship (97.83%) +50",
            "Batch Creation detected (std: 0.114309) +15",
            "Low Social interaction (0.00%) +10",
            "Very Low Trust Score (avg: 0.80) +20"
          ]
        }
      },
      {
        "id": "0x19487d63cd790ac6ab8e186932b6c87753f02011",
        "risk_label": "MALICIOUS",
        "cluster_id": 0,
        "risk_score": 0.95,
        "attributes": {
          "handle": "manel3289",
          "trust_score": 6.36,
          "follower_count": 0,
          "post_count": 0,
          "picture_url": "lens://6543fa708a402c320ede2a827e46b84a163aa34a46eca44f2698cbf96330a88b",
          "owned_by": "0xea7dc52627932f5572b01d1f3935dfeb95bbf58d",
          "reasons": [
            "High Co-owner relationship (97.83%) +50",
            "Batch Creation detected (std: 0.114309) +15",
            "Low Social interaction (0.00%) +10",
            "Very Low Trust Score (avg: 0.80) +20"
          ]
        }
      },
      {
        "id": "0x7efa24fc75075cf6d28671aee9aac9ebf8134d66",
        "risk_label": "MALICIOUS",
        "cluster_id": 0,
        "risk_score": 0.95,
        "attributes": {
          "handle": "greginhere",
          "trust_score": 0.22,
          "follower_count": 0,
          "post_count": 0,
          "picture_url": "",
          "owned_by": "0x7d78cd9438165feb80057437802aec2a218863ae",
          "reasons": [
            "High Co-owner relationship (97.83%) +50",
            "Batch Creation detected (std: 0.114309) +15",
            "Low Social interaction (0.00%) +10",
            "Very Low Trust Score (avg: 0.80) +20"
          ]
        }
      },
      {
        "id": "0x382be3dc2539c2d419704b468a1e2df7ea4a04d0",
        "risk_label": "MALICIOUS",
        "cluster_id": 0,
        "risk_score": 0.95,
        "attributes": {
          "handle": "gtsmmny",
          "trust_score": 0.21,
          "follower_count": 0,
          "post_count": 0,
          "picture_url": "",
          "owned_by": "0x7d78cd9438165feb80057437802aec2a218863ae",
          "reasons": [
            "High Co-owner relationship (97.83%) +50",
            "Batch Creation detected (std: 0.114309) +15",
            "Low Social interaction (0.00%) +10",
            "Very Low Trust Score (avg: 0.80) +20"
          ]
        }
      },
      {
        "id": "0x98e33655d33fffc1380f79a43bc14cd85f84b7b4",
        "risk_label": "MALICIOUS",
        "cluster_id": 0,
        "risk_score": 0.95,
        "attributes": {
          "handle": "lemonfck",
          "trust_score": 0.24,
          "follower_count": 0,
          "post_count": 1,
          "picture_url": "",
          "owned_by": "0x7d78cd9438165feb80057437802aec2a218863ae",
          "reasons": [
            "High Co-owner relationship (97.83%) +50",
            "Batch Creation detected (std: 0.114309) +15",
            "Low Social interaction (0.00%) +10",
            "Very Low Trust Score (avg: 0.80) +20"
          ]
        }
      },
      {
        "id": "0x84335c4cca84378d59c761db1ec6a6ca2dab102e",
        "risk_label": "BENIGN",
        "cluster_id": 1,
        "risk_score": 0.0,
        "attributes": {
          "handle": "emmajane1313",
          "trust_score": 99.74,
          "follower_count": 1348,
          "post_count": 0,
          "picture_url": "https://gw.ipfs-lens.dev/ipfs/bafkreiborp35hwyg3lkaldu6lg3mmelfhkdrrgofopclj6z6s2rt3ea3ke",
          "owned_by": "0x70209107aa82cc0cf95c3caf84ec164e7e1ac32a",
          "reasons": []
        }
      },
      {
        "id": "0xdef44af9b09ffce0d9e7e1499d797485340d40c9",
        "risk_label": "MALICIOUS",
        "cluster_id": 4,
        "risk_score": 0.95,
        "attributes": {
          "handle": "sicon",
          "trust_score": 0.26,
          "follower_count": 0,
          "post_count": 0,
          "picture_url": "",
          "owned_by": "0xd5519052f1ce7a90538c97a891da525bdef8691b",
          "reasons": [
            "High Co-owner relationship (100.00%) +50",
            "Batch Creation detected (std: 0.030537) +15",
            "Low Social interaction (0.00%) +10",
            "Very Low Trust Score (avg: 0.26) +20"
          ]
        }
      },
      {
        "id": "0x9b2ea85d30b641dce85748c7e6083853cbfd0364",
        "risk_label": "MALICIOUS",
        "cluster_id": 4,
        "risk_score": 0.95,
        "attributes": {
          "handle": "axi2k",
          "trust_score": 0.26,
          "follower_count": 0,
          "post_count": 0,
          "picture_url": "",
          "owned_by": "0xd5519052f1ce7a90538c97a891da525bdef8691b",
          "reasons": [
            "High Co-owner relationship (100.00%) +50",
            "Batch Creation detected (std: 0.030537) +15",
            "Low Social interaction (0.00%) +10",
            "Very Low Trust Score (avg: 0.26) +20"
          ]
        }
      },
      {
        "id": "0xa7a0198f52e1166f6e854b3d2b5de51b998fd6bc",
        "risk_label": "BENIGN",
        "cluster_id": 1,
        "risk_score": 0.0,
        "attributes": {
          "handle": "xverx",
          "trust_score": 6.48,
          "follower_count": 1324,
          "post_count": 4601,
          "picture_url": "https://ik.imagekit.io/lens/597957a386a70c74acec880b22c215f9e59a14551d649f0d6545a6349ba3d08e_d7X7e-iG_.webp",
          "owned_by": "0x50b68702548fd2bfde1c4c02129cb2ce7067b2c4",
          "reasons": []
        }
      },
      {
        "id": "0x0464c6772455f95feaf0ba14f4cb705e53d6fd6f",
        "risk_label": "HIGH_RISK",
        "cluster_id": 3,
        "risk_score": 0.75,
        "attributes": {
          "handle": "alexchencrypto",
          "trust_score": 9.94,
          "follower_count": 0,
          "post_count": 0,
          "picture_url": "https://api.grove.storage/036c4dd81d6a49a23e7b076d93f88ecf353b2ebcdd6a14fc989ab2aa86a11009",
          "owned_by": "0x3f398e179754df0a8bf4ac5db7abb9b86f4e689b",
          "reasons": [
            "High Co-owner relationship (100.00%) +50",
            "Batch Creation detected (std: 0.112716) +15",
            "Low Social interaction (0.00%) +10"
          ]
        }
      },
      {
        "id": "0xb04750caf69cccdc8f5af5adadfa8555080c431a",
        "risk_label": "HIGH_RISK",
        "cluster_id": 3,
        "risk_score": 0.75,
        "attributes": {
          "handle": "city_alexchen",
          "trust_score": 9.94,
          "follower_count": 0,
          "post_count": 0,
          "picture_url": "https://api.grove.storage/840c7389e24968b107dfc3291be98f887b68d96c4e46abb3088a785334577f60",
          "owned_by": "0x3f398e179754df0a8bf4ac5db7abb9b86f4e689b",
          "reasons": [
            "High Co-owner relationship (100.00%) +50",
            "Batch Creation detected (std: 0.112716) +15",
            "Low Social interaction (0.00%) +10"
          ]
        }
      }
    ],
    "links": [
      {
        "source": "0xa7a0198f52e1166f6e854b3d2b5de51b998fd6bc",
        "target": "0x84335c4cca84378d59c761db1ec6a6ca2dab102e",
        "edge_type": "FOLLOW",
        "weight": 2.0
      },
      {
        "source": "0x0464c6772455f95feaf0ba14f4cb705e53d6fd6f",
        "target": "0xb04750caf69cccdc8f5af5adadfa8555080c431a",
        "edge_type": "CO-OWNER",
        "weight": 5.0
      },
      {
        "source": "0xf46bfb21ccb72e83db06b23d3f05e86b3e259efd",
        "target": "0xffcb4b09f394f452c5100f0152cef89aede9973c",
        "edge_type": "CO-OWNER",
        "weight": 5.0
      },
      {
        "source": "0xb88c8ffb879f1e1aba113ae730cd7a4c0e56e3ab",
        "target": "0x96924fb77ec718a740cf97519dff4b2dda52b474",
        "edge_type": "CO-OWNER",
        "weight": 5.0
      },
      {
        "source": "0xb88c8ffb879f1e1aba113ae730cd7a4c0e56e3ab",
        "target": "0xb9cd598d4fd15c13610b79699828d4290410d2a9",
        "edge_type": "CO-OWNER",
        "weight": 5.0
      },
      {
        "source": "0xb88c8ffb879f1e1aba113ae730cd7a4c0e56e3ab",
        "target": "0x4e5d4fe07250979a03c24c37f69cc83b77f2a008",
        "edge_type": "CO-OWNER",
        "weight": 5.0
      },
      {
        "source": "0xb88c8ffb879f1e1aba113ae730cd7a4c0e56e3ab",
        "target": "0x63cff7128d00d024ee724b6f66af1c2a20f69fd8",
        "edge_type": "CO-OWNER",
        "weight": 5.0
      },
      {
        "source": "0xb88c8ffb879f1e1aba113ae730cd7a4c0e56e3ab",
        "target": "0xf552d2f3046b41493e8123484c5603358b228de2",
        "edge_type": "CO-OWNER",
        "weight": 5.0
      },
      {
        "source": "0xb88c8ffb879f1e1aba113ae730cd7a4c0e56e3ab",
        "target": "0xc905e7b845826dd473f42bae8a2cddbe2c630420",
        "edge_type": "CO-OWNER",
        "weight": 5.0
      },
      {
        "source": "0xb88c8ffb879f1e1aba113ae730cd7a4c0e56e3ab",
        "target": "0x7efa24fc75075cf6d28671aee9aac9ebf8134d66",
        "edge_type": "CO-OWNER",
        "weight": 5.0
      },
      {
        "source": "0xb88c8ffb879f1e1aba113ae730cd7a4c0e56e3ab",
        "target": "0x382be3dc2539c2d419704b468a1e2df7ea4a04d0",
        "edge_type": "CO-OWNER",
        "weight": 5.0
      },
      {
        "source": "0xb88c8ffb879f1e1aba113ae730cd7a4c0e56e3ab",
        "target": "0x98e33655d33fffc1380f79a43bc14cd85f84b7b4",
        "edge_type": "CO-OWNER",
        "weight": 5.0
      },
      {
        "source": "0x96924fb77ec718a740cf97519dff4b2dda52b474",
        "target": "0xb9cd598d4fd15c13610b79699828d4290410d2a9",
        "edge_type": "CO-OWNER",
        "weight": 5.0
      },
      {
        "source": "0x96924fb77ec718a740cf97519dff4b2dda52b474",
        "target": "0x4e5d4fe07250979a03c24c37f69cc83b77f2a008",
        "edge_type": "CO-OWNER",
        "weight": 5.0
      },
      {
        "source": "0x96924fb77ec718a740cf97519dff4b2dda52b474",
        "target": "0x63cff7128d00d024ee724b6f66af1c2a20f69fd8",
        "edge_type": "CO-OWNER",
        "weight": 5.0
      },
      {
        "source": "0x96924fb77ec718a740cf97519dff4b2dda52b474",
        "target": "0xf552d2f3046b41493e8123484c5603358b228de2",
        "edge_type": "CO-OWNER",
        "weight": 5.0
      },
      {
        "source": "0x96924fb77ec718a740cf97519dff4b2dda52b474",
        "target": "0xc905e7b845826dd473f42bae8a2cddbe2c630420",
        "edge_type": "CO-OWNER",
        "weight": 5.0
      },
      {
        "source": "0x96924fb77ec718a740cf97519dff4b2dda52b474",
        "target": "0x7efa24fc75075cf6d28671aee9aac9ebf8134d66",
        "edge_type": "CO-OWNER",
        "weight": 5.0
      },
      {
        "source": "0x96924fb77ec718a740cf97519dff4b2dda52b474",
        "target": "0x382be3dc2539c2d419704b468a1e2df7ea4a04d0",
        "edge_type": "CO-OWNER",
        "weight": 5.0
      },
      {
        "source": "0x96924fb77ec718a740cf97519dff4b2dda52b474",
        "target": "0x98e33655d33fffc1380f79a43bc14cd85f84b7b4",
        "edge_type": "CO-OWNER",
        "weight": 5.0
      },
      {
        "source": "0xb9cd598d4fd15c13610b79699828d4290410d2a9",
        "target": "0x4e5d4fe07250979a03c24c37f69cc83b77f2a008",
        "edge_type": "CO-OWNER",
        "weight": 5.0
      },
      {
        "source": "0xb9cd598d4fd15c13610b79699828d4290410d2a9",
        "target": "0x63cff7128d00d024ee724b6f66af1c2a20f69fd8",
        "edge_type": "CO-OWNER",
        "weight": 5.0
      },
      {
        "source": "0xb9cd598d4fd15c13610b79699828d4290410d2a9",
        "target": "0xf552d2f3046b41493e8123484c5603358b228de2",
        "edge_type": "CO-OWNER",
        "weight": 5.0
      },
      {
        "source": "0xb9cd598d4fd15c13610b79699828d4290410d2a9",
        "target": "0xc905e7b845826dd473f42bae8a2cddbe2c630420",
        "edge_type": "CO-OWNER",
        "weight": 5.0
      },
      {
        "source": "0xb9cd598d4fd15c13610b79699828d4290410d2a9",
        "target": "0x7efa24fc75075cf6d28671aee9aac9ebf8134d66",
        "edge_type": "CO-OWNER",
        "weight": 5.0
      },
      {
        "source": "0xb9cd598d4fd15c13610b79699828d4290410d2a9",
        "target": "0x382be3dc2539c2d419704b468a1e2df7ea4a04d0",
        "edge_type": "CO-OWNER",
        "weight": 5.0
      },
      {
        "source": "0xb9cd598d4fd15c13610b79699828d4290410d2a9",
        "target": "0x98e33655d33fffc1380f79a43bc14cd85f84b7b4",
        "edge_type": "CO-OWNER",
        "weight": 5.0
      },
      {
        "source": "0x4e5d4fe07250979a03c24c37f69cc83b77f2a008",
        "target": "0x63cff7128d00d024ee724b6f66af1c2a20f69fd8",
        "edge_type": "CO-OWNER",
        "weight": 5.0
      },
      {
        "source": "0x4e5d4fe07250979a03c24c37f69cc83b77f2a008",
        "target": "0xf552d2f3046b41493e8123484c5603358b228de2",
        "edge_type": "CO-OWNER",
        "weight": 5.0
      },
      {
        "source": "0x4e5d4fe07250979a03c24c37f69cc83b77f2a008",
        "target": "0xc905e7b845826dd473f42bae8a2cddbe2c630420",
        "edge_type": "CO-OWNER",
        "weight": 5.0
      },
      {
        "source": "0x4e5d4fe07250979a03c24c37f69cc83b77f2a008",
        "target": "0x7efa24fc75075cf6d28671aee9aac9ebf8134d66",
        "edge_type": "CO-OWNER",
        "weight": 5.0
      },
      {
        "source": "0x4e5d4fe07250979a03c24c37f69cc83b77f2a008",
        "target": "0x382be3dc2539c2d419704b468a1e2df7ea4a04d0",
        "edge_type": "CO-OWNER",
        "weight": 5.0
      },
      {
        "source": "0x4e5d4fe07250979a03c24c37f69cc83b77f2a008",
        "target": "0x98e33655d33fffc1380f79a43bc14cd85f84b7b4",
        "edge_type": "CO-OWNER",
        "weight": 5.0
      },
      {
        "source": "0x63cff7128d00d024ee724b6f66af1c2a20f69fd8",
        "target": "0xf552d2f3046b41493e8123484c5603358b228de2",
        "edge_type": "CO-OWNER",
        "weight": 5.0
      },
      {
        "source": "0x63cff7128d00d024ee724b6f66af1c2a20f69fd8",
        "target": "0xc905e7b845826dd473f42bae8a2cddbe2c630420",
        "edge_type": "CO-OWNER",
        "weight": 5.0
      },
      {
        "source": "0x63cff7128d00d024ee724b6f66af1c2a20f69fd8",
        "target": "0x7efa24fc75075cf6d28671aee9aac9ebf8134d66",
        "edge_type": "CO-OWNER",
        "weight": 5.0
      },
      {
        "source": "0x63cff7128d00d024ee724b6f66af1c2a20f69fd8",
        "target": "0x382be3dc2539c2d419704b468a1e2df7ea4a04d0",
        "edge_type": "CO-OWNER",
        "weight": 5.0
      },
      {
        "source": "0x63cff7128d00d024ee724b6f66af1c2a20f69fd8",
        "target": "0x98e33655d33fffc1380f79a43bc14cd85f84b7b4",
        "edge_type": "CO-OWNER",
        "weight": 5.0
      },
      {
        "source": "0xf552d2f3046b41493e8123484c5603358b228de2",
        "target": "0xc905e7b845826dd473f42bae8a2cddbe2c630420",
        "edge_type": "CO-OWNER",
        "weight": 5.0
      },
      {
        "source": "0xf552d2f3046b41493e8123484c5603358b228de2",
        "target": "0x7efa24fc75075cf6d28671aee9aac9ebf8134d66",
        "edge_type": "CO-OWNER",
        "weight": 5.0
      },
      {
        "source": "0xf552d2f3046b41493e8123484c5603358b228de2",
        "target": "0x382be3dc2539c2d419704b468a1e2df7ea4a04d0",
        "edge_type": "CO-OWNER",
        "weight": 5.0
      },
      {
        "source": "0xf552d2f3046b41493e8123484c5603358b228de2",
        "target": "0x98e33655d33fffc1380f79a43bc14cd85f84b7b4",
        "edge_type": "CO-OWNER",
        "weight": 5.0
      },
      {
        "source": "0xc905e7b845826dd473f42bae8a2cddbe2c630420",
        "target": "0x7efa24fc75075cf6d28671aee9aac9ebf8134d66",
        "edge_type": "CO-OWNER",
        "weight": 5.0
      },
      {
        "source": "0xc905e7b845826dd473f42bae8a2cddbe2c630420",
        "target": "0x382be3dc2539c2d419704b468a1e2df7ea4a04d0",
        "edge_type": "CO-OWNER",
        "weight": 5.0
      },
      {
        "source": "0xc905e7b845826dd473f42bae8a2cddbe2c630420",
        "target": "0x98e33655d33fffc1380f79a43bc14cd85f84b7b4",
        "edge_type": "CO-OWNER",
        "weight": 5.0
      },
      {
        "source": "0x7efa24fc75075cf6d28671aee9aac9ebf8134d66",
        "target": "0x382be3dc2539c2d419704b468a1e2df7ea4a04d0",
        "edge_type": "CO-OWNER",
        "weight": 5.0
      },
      {
        "source": "0x7efa24fc75075cf6d28671aee9aac9ebf8134d66",
        "target": "0x98e33655d33fffc1380f79a43bc14cd85f84b7b4",
        "edge_type": "CO-OWNER",
        "weight": 5.0
      },
      {
        "source": "0x382be3dc2539c2d419704b468a1e2df7ea4a04d0",
        "target": "0x98e33655d33fffc1380f79a43bc14cd85f84b7b4",
        "edge_type": "CO-OWNER",
        "weight": 5.0
      },
      {
        "source": "0xdef44af9b09ffce0d9e7e1499d797485340d40c9",
        "target": "0x9b2ea85d30b641dce85748c7e6083853cbfd0364",
        "edge_type": "CO-OWNER",
        "weight": 5.0
      },
      {
        "source": "0x7efa24fc75075cf6d28671aee9aac9ebf8134d66",
        "target": "0x19487d63cd790ac6ab8e186932b6c87753f02011",
        "edge_type": "SIMILARITY",
        "weight": 3.0
      }
    ],
    "cluster_count": 5
  },
  "message": null
}
